setup.py
loopyCryptor/Cryptor.py
loopyCryptor/Serializer.py
loopyCryptor/__init__.py
loopyCryptor.egg-info/PKG-INFO
loopyCryptor.egg-info/SOURCES.txt
loopyCryptor.egg-info/dependency_links.txt
loopyCryptor.egg-info/requires.txt
loopyCryptor.egg-info/top_level.txt
test/test.py