Metadata-Version: 1.2
Name: loopyCryptor
Version: 0.1.0
Summary: Easy-to-use string symmetric/asymmetric encryption tools based on PyCryptodome
Home-page: UNKNOWN
Author: loopyme
Author-email: peter@mail.loopy.tech
Maintainer: loopyme
Maintainer-email: peter@mail.loopy.tech
License: MIT License
Platform: all
